commandbased/__init__.py
commandbased/cancelcommand.py
commandbased/commandbasedrobot.py
commandbased/flowcontrol.py
commands1/__init__.py
commands1/py.typed
commands1/version.py
commands1/_impl/__init__.py
commands1/_impl/_commands_v1.cpython-38-x86_64-linux-gnu.so
commands1/_impl/_init_commands_v1.py
commands1/_impl/command.cpp
commands1/_impl/pkgcfg.py
commands1/_impl/__pycache__/__init__.cpython-38.pyc
commands1/_impl/__pycache__/_init_commands_v1.cpython-38.pyc
commands1/_impl/_commands_v1/__init__.pyi
commands1/_impl/_commands_v1/button/__init__.pyi
commands1/_impl/_commands_v1/command/__init__.pyi
commands1/_impl/include/frc/PIDBase.h
commands1/_impl/include/frc/PIDController.h
commands1/_impl/include/frc/PIDInterface.h
commands1/_impl/include/frc/PIDOutput.h
commands1/_impl/include/frc/PIDSource.h
commands1/_impl/include/frc/buttons/Button.h
commands1/_impl/include/frc/buttons/ButtonScheduler.h
commands1/_impl/include/frc/buttons/CancelButtonScheduler.h
commands1/_impl/include/frc/buttons/HeldButtonScheduler.h
commands1/_impl/include/frc/buttons/InternalButton.h
commands1/_impl/include/frc/buttons/JoystickButton.h
commands1/_impl/include/frc/buttons/NetworkButton.h
commands1/_impl/include/frc/buttons/POVButton.h
commands1/_impl/include/frc/buttons/PressedButtonScheduler.h
commands1/_impl/include/frc/buttons/ReleasedButtonScheduler.h
commands1/_impl/include/frc/buttons/ToggleButtonScheduler.h
commands1/_impl/include/frc/buttons/Trigger.h
commands1/_impl/include/frc/commands/Command.h
commands1/_impl/include/frc/commands/CommandGroup.h
commands1/_impl/include/frc/commands/CommandGroupEntry.h
commands1/_impl/include/frc/commands/ConditionalCommand.h
commands1/_impl/include/frc/commands/InstantCommand.h
commands1/_impl/include/frc/commands/PIDCommand.h
commands1/_impl/include/frc/commands/PIDSubsystem.h
commands1/_impl/include/frc/commands/PrintCommand.h
commands1/_impl/include/frc/commands/Scheduler.h
commands1/_impl/include/frc/commands/StartCommand.h
robotpy_commands_v1-2022.4.1.0.dist-info/METADATA
robotpy_commands_v1-2022.4.1.0.dist-info/WHEEL
robotpy_commands_v1-2022.4.1.0.dist-info/entry_points.txt
robotpy_commands_v1-2022.4.1.0.dist-info/top_level.txt
robotpy_commands_v1-2022.4.1.0.dist-info/RECORD
