Metadata-Version: 2.1
Name: robotpy-commands-v1
Version: 2022.4.1.0
Summary: WPILib command framework
Home-page: https://github.com/robotpy/robotpy-commands
Author: RobotPy Development Team
Author-email: robotpy@googlegroups.com
License: BSD-3-Clause
Platform: UNKNOWN
Requires-Python: >=3.6
Requires-Dist: wpilib (<2023.0.0,>=2022.4.1.0)
